solution_harsha/__init__.py
solution_harsha/config.yaml
solution_harsha/di_testcode.py
solution_harsha-0.10.dist-info/METADATA
solution_harsha-0.10.dist-info/WHEEL
solution_harsha-0.10.dist-info/entry_points.txt
solution_harsha-0.10.dist-info/top_level.txt
solution_harsha-0.10.dist-info/RECORD
