Metadata-Version: 2.1
Name: solution-harsha
Version: 0.10
Summary: A tool for performing string matching on text files
Author: Sriharsha Aryasomayajula
Author-email: harshaarya17@outlook.com
Requires-Dist: ruamel.yaml
Requires-Dist: regex
Requires-Dist: argparse
